trojanvision/__init__.py
trojanvision/environ.py
trojanvision/trainer.py
trojanvision/attacks/__init__.py
trojanvision/attacks/abstract.py
trojanvision/attacks/adv/__init__.py
trojanvision/attacks/adv/pgd.py
trojanvision/attacks/backdoor/__init__.py
trojanvision/attacks/backdoor/clean_label/__init__.py
trojanvision/attacks/backdoor/clean_label/clean_label.py
trojanvision/attacks/backdoor/clean_label/invisible_poison.py
trojanvision/attacks/backdoor/clean_label/label_consistent.py
trojanvision/attacks/backdoor/clean_label/refool.py
trojanvision/attacks/backdoor/dynamic/__init__.py
trojanvision/attacks/backdoor/dynamic/input_aware_dynamic.py
trojanvision/attacks/backdoor/normal/__init__.py
trojanvision/attacks/backdoor/normal/badnet.py
trojanvision/attacks/backdoor/normal/imc.py
trojanvision/attacks/backdoor/normal/latent_backdoor.py
trojanvision/attacks/backdoor/normal/trojannet.py
trojanvision/attacks/backdoor/normal/trojannn.py
trojanvision/attacks/backdoor/others/__init__.py
trojanvision/attacks/backdoor/others/unlearn.py
trojanvision/attacks/poison/__init__.py
trojanvision/attacks/poison/imc_poison.py
trojanvision/attacks/poison/poison_basic.py
trojanvision/attacks/poison/poison_random.py
trojanvision/configs/__init__.py
trojanvision/configs/dataset.yml
trojanvision/configs/model.yml
trojanvision/configs/trainer.yml
trojanvision/data/cub200/test.txt
trojanvision/data/cub200/train.txt
trojanvision/data/cub200_2011/images.txt
trojanvision/data/cub200_2011/train_test_split.txt
trojanvision/data/isic2018/train.csv
trojanvision/data/isic2018/valid.csv
trojanvision/data/refool/insert_reflection.py
trojanvision/data/sample_imagenet/class_dict.json
trojanvision/data/stl10/unlabeled_y.bin
trojanvision/datasets/__init__.py
trojanvision/datasets/imagefolder.py
trojanvision/datasets/imageset.py
trojanvision/datasets/folder/__init__.py
trojanvision/datasets/folder/cub200.py
trojanvision/datasets/folder/gtsrb.py
trojanvision/datasets/folder/imagenet.py
trojanzoo-2.0.3.dist-info/LICENSE
trojanzoo-2.0.3.dist-info/METADATA
trojanzoo-2.0.3.dist-info/WHEEL
trojanzoo-2.0.3.dist-info/top_level.txt
trojanzoo-2.0.3.dist-info/RECORD
