Metadata-Version: 2.1
Name: trojanzoo
Version: 2.0.3
Summary: a universal pytorch platform to conduct security researches
Home-page: https://github.com/ain-soph/trojanzoo
Author: Ren Pang
Author-email: rbp5354@psu.edu
License: GPL-3
Keywords: pytorch,image classification,backdoor attack/defense
Classifier: Environment :: GPU :: NVIDIA CUDA :: 11.3
Classifier: Intended Audience :: Developers
Classifier: Intended Audience :: Education
Classifier: Intended Audience :: Science/Research
Classifier: License :: OSI Approved :: GNU General Public License v3 (GPLv3)
Classifier: Topic :: Scientific/Engineering :: Artificial Intelligence
Classifier: Topic :: Scientific/Engineering :: Image Recognition
Classifier: Topic :: Software Development :: Libraries :: Python Modules
Classifier: Programming Language :: Python :: 3.10
Requires-Python: >=3.11
License-File: LICENSE
Requires-Dist: torch >=1.12.1
Requires-Dist: torchvision >=0.13.1
Requires-Dist: numpy >=1.22
Requires-Dist: matplotlib >=3.4.2
Requires-Dist: scikit-image >=0.19.2
Requires-Dist: scikit-learn >=0.24.0
Requires-Dist: scipy >=1.5.4
Requires-Dist: pyyaml >=5.3.1
Requires-Dist: pandas >=1.1.5
Requires-Dist: tqdm >=4.54.1
